pyucrop/__init__.py
pyucrop/clients/client.py
pyucrop/clients/exceptions.py
pyucrop/clients/__pycache__/client.cpython-38.pyc
pyucrop/clients/__pycache__/exceptions.cpython-38.pyc
pyucrop-1.0.2.dist-info/METADATA
pyucrop-1.0.2.dist-info/WHEEL
pyucrop-1.0.2.dist-info/top_level.txt
pyucrop-1.0.2.dist-info/RECORD
